flask_streamy/__init__.py
flask_streamy/sse.py
flask_streamy/stream_manager.py
tests/__init__.py
tests/test_flask_streamy.py
flask_streamy-0.1.0.dist-info/LICENSE
flask_streamy-0.1.0.dist-info/METADATA
flask_streamy-0.1.0.dist-info/WHEEL
flask_streamy-0.1.0.dist-info/top_level.txt
flask_streamy-0.1.0.dist-info/RECORD
