Metadata-Version: 2.1
Name: flask-streamy
Version: 0.1.0
Summary: A Flask package for managing SSE streams.
Home-page: https://github.com/snickdx/flask-streamy
Author: Nicholas Mendez
Author-email: snickdx@gmail.com
Classifier: Programming Language :: Python :: 3
Classifier: License :: OSI Approved :: MIT License
Classifier: Operating System :: OS Independent
License-File: LICENSE
Requires-Dist: Flask>=2.0
